keyrings/__init__.py
keyrings/osx_keychain_keys/__init__.py
keyrings/osx_keychain_keys/backend.py
keyrings/osx_keychain_keys/examples/__init__.py
keyrings/osx_keychain_keys/examples/backend_example.py
keyrings/osx_keychain_keys/tests/3des_encrypted.key
keyrings/osx_keychain_keys/tests/__init__.py
keyrings/osx_keychain_keys/tests/aes_128_encrypted.key
keyrings/osx_keychain_keys/tests/des_encrypted.key
keyrings/osx_keychain_keys/tests/test_keychain_keys.py
keyrings.osx_keychain_keys-1.0.1.dist-info/LICENSE
keyrings.osx_keychain_keys-1.0.1.dist-info/METADATA
keyrings.osx_keychain_keys-1.0.1.dist-info/WHEEL
keyrings.osx_keychain_keys-1.0.1.dist-info/entry_points.txt
keyrings.osx_keychain_keys-1.0.1.dist-info/top_level.txt
keyrings.osx_keychain_keys-1.0.1.dist-info/RECORD
