Metadata-Version: 2.1
Name: keyrings.osx-keychain-keys
Version: 1.0.1
Summary: OSX Keychain backend for key-pairs
Home-page: https://github.com/dany74q/keyrings.osx_keychain_keys
Author: Danny Shemesh
Author-email: dany74q@gmail.com
License: UNKNOWN
Platform: UNKNOWN
Classifier: Development Status :: 5 - Production/Stable
Classifier: Intended Audience :: Developers
Classifier: License :: OSI Approved :: MIT License
Classifier: Programming Language :: Python :: 3
Requires-Python: >=3.6
Requires-Dist: pyobjc-framework-Security (>=6.2.2)
Requires-Dist: pyobjc-framework-Cocoa (>=6.2.2)
Requires-Dist: cryptography (>=3.1)
Requires-Dist: keyring (>=21.4.0)
Provides-Extra: docs
Requires-Dist: sphinx (>=3.2.1) ; extra == 'docs'
Requires-Dist: jaraco.packaging (>=3.2) ; extra == 'docs'
Requires-Dist: rst.linker (>=2.0.0) ; extra == 'docs'
Provides-Extra: testing
Requires-Dist: pytest (>=6.0.1) ; extra == 'testing'
Requires-Dist: pytest-flake8 (>=1.0.6) ; extra == 'testing'
Requires-Dist: pytest-black (>=0.3.11) ; extra == 'testing'
Requires-Dist: pytest-cov (>=2.10.1) ; extra == 'testing'
